{
  "_note": "网易红彩免费专家方案(世界杯) + 详情。unlocked=true 含正文/推荐/赔率/专家战绩/近期走势；false 仅元信息+深链。展示须标注：专家观点来自第三方·仅供参考·理性购彩·18+。",
  "_source": "hongcai.163.com /api/web/free/0/9999 + /thread/query/{id}/0",
  "_fetchedAt": "2026-06-24T00:01:59.015Z",
  "total": 6,
  "unlocked": 4,
  "plans": [
    {
      "threadId": 3502856,
      "title": "【瑞士VS加拿大】和别人不一样的解题思路600字详细剖析，双方各拿一分携手出线？",
      "publishTime": "11小时前发布",
      "free": true,
      "price": 0,
      "previousPrice": 88,
      "type": "单场",
      "matchNum": 1,
      "matchZh": "瑞士 vs 加拿大",
      "home": "Switzerland",
      "away": "Canada",
      "matchTime": "06/25",
      "matchInfoId": 5403444,
      "expert": {
        "name": "廖佳豪",
        "avatar": "https://relottery.ws.126.net/user/snapshot/20260117/TkaPceX.png",
        "slogan": "实战达人",
        "desc": "深耕足球、篮球行业多年，常年研究数据走势，擅长足球领域英超、德甲，篮球领域NBA和WNBA",
        "hitRate": 1,
        "recent": "近2场中2场",
        "follower": 901,
        "planCount": 42,
        "maxWin": 10
      },
      "link": "https://hongcai.163.com/thread.html?threadId=3502856",
      "unlocked": true,
      "content": "<p>首先来介绍一下B组的出线形式，目前加拿大以净胜球的优势排在第一，瑞士第二，那么B组的第一将会去面对E\\F\\G\\I\\J组的第三，顺位按照世界排名来，排名最高的讲对阵B组的第一，那么我们来看一下这六个小组的第三，首先E组这边基本上就是厄瓜多尔，F组可能是日本或者瑞典，G组基本上是伊朗，I组会是塞内加尔，J组则可能是阿尔及利亚或者奥地利，按照世界排名先后，塞内加尔第15名最靠前，将对阵B组第一。B组的第二将面对A组的第二，基本已经锁定是韩国了。</p><p>我们再来看瑞士，通过前面两轮看得出，瑞士在进攻端火力确实是很凶猛的，两场比赛的预期进球高达5.26，创造了10次的绝佳破门机会，但是防线上整体身高在185，转身回追速度慢的短板已经暴露的很明显了，热身赛面对澳大利亚，首轮面对卡塔尔都是同样的问题导致丢球。那么对于瑞士来说是不是很不愿意面对亚洲球队韩国的小快灵锋线，所以我认为瑞士可能更愿意面对非洲球队塞内加尔，是有理由冲击小组第一的。</p><p>再来看加拿大，加拿大在面对卡塔尔的时候损失了中场核心科内，已经完成手术，确定无缘世界杯了。那么科内在整个球队的体系中扮演的角色是很重要的，他可以说是全能型的中场，少了他首先就是中场第一道防线屏障将大打折扣，然后就是攻防转换的发动机没有了，以及后排插上的二点远射没有了。再加上阿方索戴维斯目前还是没能达到痊愈的状态，我认为加拿大最后一轮在缺少科内后，做出阵容调试是比较合理的。</p><p>情绪方面我认为初始对于瑞士的态度也是比较强硬的，所以本场我认为瑞士更加值得期待</p>",
      "recommends": [
        {
          "play": "让球",
          "code": "HDA",
          "items": [
            {
              "name": "主胜",
              "odds": 2.3,
              "rec": true
            },
            {
              "name": "平",
              "odds": 2.62,
              "rec": false
            },
            {
              "name": "客胜",
              "odds": 3.2,
              "rec": false
            }
          ]
        },
        {
          "play": "比分",
          "code": "FBF",
          "items": [
            {
              "name": "3:1",
              "odds": 18,
              "rec": true
            },
            {
              "name": "2:1",
              "odds": 8,
              "rec": true
            }
          ]
        }
      ],
      "recentForm": [
        {
          "date": "26-06-19",
          "home": "瑞士",
          "hs": 4,
          "as": 1,
          "away": "波黑",
          "half": "0-0",
          "handicap": -1,
          "ou": 2.5
        },
        {
          "date": "26-06-14",
          "home": "卡塔尔",
          "hs": 1,
          "as": 1,
          "away": "瑞士",
          "half": "0-1",
          "handicap": 1.25,
          "ou": 2.75
        },
        {
          "date": "26-06-07",
          "home": "澳大利亚",
          "hs": 1,
          "as": 1,
          "away": "瑞士",
          "half": "0-1",
          "handicap": 1,
          "ou": 2.5
        },
        {
          "date": "26-05-31",
          "home": "瑞士",
          "hs": 4,
          "as": 1,
          "away": "约旦",
          "half": "3-0",
          "handicap": -1.5,
          "ou": 3
        }
      ],
      "jcNum": "周三049",
      "homeIcon": "https://relottery.ws.126.net/thread/snapshot/20260402/jYGhu8r.png",
      "awayIcon": "https://relottery.ws.126.net/thread/snapshot/20260402/bDPotmH.png"
    },
    {
      "threadId": 3503012,
      "title": "免费 6月24日【世界杯】瑞士 VS 加拿大！",
      "publishTime": "1小时前发布",
      "free": true,
      "price": 0,
      "previousPrice": 88,
      "type": "单场",
      "matchNum": 1,
      "matchZh": "瑞士 vs 加拿大",
      "home": "Switzerland",
      "away": "Canada",
      "matchTime": "06/25",
      "matchInfoId": 5403444,
      "expert": {
        "name": "戴维",
        "avatar": "https://relottery.ws.126.net/user/20170320/oGb4fz.jpg",
        "slogan": "足球分析师",
        "desc": "资深专家，独家创建“形态、进球差、误差”三大理论分析比赛，理论及实战经验丰富。",
        "hitRate": 0.53,
        "recent": "近15场中8场",
        "follower": 25910,
        "planCount": 47,
        "maxWin": 11
      },
      "link": "https://hongcai.163.com/thread.html?threadId=3503012",
      "unlocked": false,
      "content": "",
      "recommends": [],
      "recentForm": [],
      "jcNum": "",
      "homeIcon": "",
      "awayIcon": ""
    },
    {
      "threadId": 3503002,
      "title": "巴拿马VS克罗地亚胜负场次参考",
      "publishTime": "1小时前发布",
      "free": true,
      "price": 0,
      "previousPrice": 58,
      "type": "单场",
      "matchNum": 1,
      "matchZh": "巴拿马 vs 克罗地亚",
      "home": "Panama",
      "away": "Croatia",
      "matchTime": "06/24",
      "matchInfoId": 5403442,
      "expert": {
        "name": "刘胜",
        "avatar": "https://relottery.ws.126.net/user/snapshot/20251113/6xp1Znr.jpg",
        "slogan": "足篮分析师",
        "desc": "擅长挖掘和分析数据，多维度理论与实战结合",
        "hitRate": 1,
        "recent": "近7场中7场",
        "follower": 188,
        "planCount": 41,
        "maxWin": 7
      },
      "link": "https://hongcai.163.com/thread.html?threadId=3503002",
      "unlocked": true,
      "content": "<p>在2026年美加墨世界杯L组的出线生死战中，巴拿马与克罗地亚上演了一场风格迥异的对决。赛前两队均遭遇开门黑，此役堪称“win or go home”的终极考验。</p><p><br></p><p>从数据上看，这是一场典型的“控球与反击”的博弈。克罗地亚展现了其传统强队的控制力，场均控球率高达65.2%，传球网络在中圈到禁区弧顶运转流畅。而巴拿马则采取稳守反击策略，控球率仅为45.6%。</p><p><br></p><p>进攻端，克罗地亚的压制力更为明显，场均轰出18.4次射门，远超巴拿马的11.3次。格子军团的进攻效率也更高，平均每9.7次射门就能转化1个进球（转化率约10.3%），场均进球达到1.9个。相比之下，巴拿马在首轮比赛中虽有场面优势却未能破门，攻击乏力的问题暴露无遗。</p><p><br></p><p>克罗地亚近10场场均仅失1.0球，而巴拿马则高达1.6球。数据显示，巴拿马防线平均每被射门7.2次就会丢1球，远低于克罗地亚的8.5次。此外，巴拿马在世界杯决赛圈已遭遇四连败，而克罗地亚作为连续两届世界杯四强得主，在关键战的经验与底蕴上无疑占据压倒性优势。</p><p><br></p><p><br></p><p>在已经得知加纳打平英格兰，克罗地亚目标还没有积分的情况下，这场打最弱的球队是必须要拿下来的，必须拿下来，这场战意是要拉满的，以克罗地亚的底蕴来讲，打巴拿马这种球队相对来说是比较轻松的。</p><p><br></p><p><br></p><p>指数也是给到足够的尊重。</p><p><br></p><p>推荐</p><p>克罗地亚方向，主负</p><p>能赢1-3球左右。</p>",
      "recommends": [
        {
          "play": "让球",
          "code": "HDA",
          "items": [
            {
              "name": "主胜",
              "odds": 6.9,
              "rec": false
            },
            {
              "name": "平",
              "odds": 4.3,
              "rec": false
            },
            {
              "name": "客胜",
              "odds": 1.33,
              "rec": true
            }
          ]
        },
        {
          "play": "比分",
          "code": "FBF",
          "items": [
            {
              "name": "0:2",
              "odds": 5.25,
              "rec": true
            },
            {
              "name": "1:3",
              "odds": 8.8,
              "rec": true
            }
          ]
        },
        {
          "play": "半全场",
          "code": "FBQC",
          "items": [
            {
              "name": "负负",
              "odds": 1.8,
              "rec": true
            }
          ]
        }
      ],
      "recentForm": [
        {
          "date": "26-06-18",
          "home": "加纳",
          "hs": 1,
          "as": 0,
          "away": "巴拿马",
          "half": "0-0",
          "handicap": -0.5,
          "ou": 2.5
        },
        {
          "date": "26-06-07",
          "home": "巴拿马",
          "hs": 1,
          "as": 1,
          "away": "波黑",
          "half": "1-1",
          "handicap": 0.25,
          "ou": 2.25
        },
        {
          "date": "26-06-04",
          "home": "巴拿马",
          "hs": 4,
          "as": 2,
          "away": "多米尼加",
          "half": "2-0",
          "handicap": -1.75,
          "ou": 3.25
        },
        {
          "date": "26-06-01",
          "home": "巴西",
          "hs": 6,
          "as": 2,
          "away": "巴拿马",
          "half": "2-1",
          "handicap": -2.25,
          "ou": 3.25
        }
      ],
      "jcNum": "周二047",
      "homeIcon": "https://relottery.ws.126.net/thread/snapshot/20260402/DxCQYGI.png",
      "awayIcon": "https://relottery.ws.126.net/thread/snapshot/20260402/rgofn0z.png"
    },
    {
      "threadId": 3502848,
      "title": "【世界杯11中10】免费公推 点点关注 巴拿马VS克罗地亚",
      "publishTime": "12小时前发布",
      "free": true,
      "price": 0,
      "previousPrice": 58,
      "type": "单场",
      "matchNum": 1,
      "matchZh": "巴拿马 vs 克罗地亚",
      "home": "Panama",
      "away": "Croatia",
      "matchTime": "06/24",
      "matchInfoId": 5403442,
      "expert": {
        "name": "陈晨",
        "avatar": "https://relottery.ws.126.net/user/snapshot/20251205/4FxFgFc.jpg",
        "slogan": "足球分析师",
        "desc": "足球爱好者，指数分析达人，共同进步。",
        "hitRate": 0.79,
        "recent": "近14场中11场",
        "follower": 346,
        "planCount": 41,
        "maxWin": 6
      },
      "link": "https://hongcai.163.com/thread.html?threadId=3502848",
      "unlocked": true,
      "content": "<p>这是一场双方都退无可退的生死战。克罗地亚首轮2-4负于英格兰，巴拿马0-1被加纳补时绝杀，两队同积0分，谁输球基本意味着提前出局。不同的是，克罗地亚依然保持着强队的底气和战术素养，而巴拿马在缺少中场核心后，原本脆弱的攻防体系将面临更大的考验。</p><p>第一，克罗地亚的传控压制与巴拿马的防守消耗，存在层级差距。 克罗地亚场均控球率65.2%，场均射门18.4次，射门进球效率约每9.7次射门进1球，只要射门基数到位，破门是大概率事件。巴拿马场均控球率仅45.6%，被射门失球效率为7.2次/球——平均每被射7.2次就要丢1球，防线抗压上限远低于克罗地亚。当达利奇的球队持续在禁区弧顶组织进攻时，巴拿马的防线失守只是时间问题。</p><p>第二，巴拿马中场核心缺阵，反击链条断裂。 主力中场卡拉斯基利亚因伤确认缺席，他是球队由守转攻的第一出球点和定位球主罚者。失去他的调度，巴拿马的进攻将更加依赖边路单打独斗，很难对克罗地亚的防线构成实质性威胁。巴拿马全队总身价仅3455万欧元，是克罗地亚3.8亿欧元的零头，多数球员征战中北美本土联赛，大赛对抗经验严重不足。</p><p>第三，体能拐点将决定比赛走向。 巴拿马上半场场均失球仅0.4球，下半场陡升到1.2球，60分钟后的体能和纪律性会出现明显塌方。克罗地亚下半场场均进球正好是1.2球，达利奇大概率会让球队在前60分钟以控球消耗对手，把破局留给后段。莫德里奇将迎来国家队第200场里程碑，全队上下势必用一场胜利为他献礼。</p><p>综上所述小陈认为客队直接取胜。</p>",
      "recommends": [
        {
          "play": "让球",
          "code": "HDA",
          "items": [
            {
              "name": "主胜",
              "odds": 6.9,
              "rec": false
            },
            {
              "name": "平",
              "odds": 4.3,
              "rec": false
            },
            {
              "name": "客胜",
              "odds": 1.33,
              "rec": true
            }
          ]
        },
        {
          "play": "比分",
          "code": "FBF",
          "items": [
            {
              "name": "1:4",
              "odds": 22,
              "rec": true
            },
            {
              "name": "1:3",
              "odds": 9,
              "rec": true
            }
          ]
        }
      ],
      "recentForm": [
        {
          "date": "26-06-18",
          "home": "加纳",
          "hs": 1,
          "as": 0,
          "away": "巴拿马",
          "half": "0-0",
          "handicap": -0.5,
          "ou": 2.5
        },
        {
          "date": "26-06-07",
          "home": "巴拿马",
          "hs": 1,
          "as": 1,
          "away": "波黑",
          "half": "1-1",
          "handicap": 0.25,
          "ou": 2.25
        },
        {
          "date": "26-06-04",
          "home": "巴拿马",
          "hs": 4,
          "as": 2,
          "away": "多米尼加",
          "half": "2-0",
          "handicap": -1.75,
          "ou": 3.25
        },
        {
          "date": "26-06-01",
          "home": "巴西",
          "hs": 6,
          "as": 2,
          "away": "巴拿马",
          "half": "2-1",
          "handicap": -2.25,
          "ou": 3.25
        }
      ],
      "jcNum": "周二047",
      "homeIcon": "https://relottery.ws.126.net/thread/snapshot/20260402/DxCQYGI.png",
      "awayIcon": "https://relottery.ws.126.net/thread/snapshot/20260402/rgofn0z.png"
    },
    {
      "threadId": 3502444,
      "title": "连续中冷门！世界杯L组2串1：巴拿马VS克罗地亚+英格兰VS加纳",
      "publishTime": "06-23 03:03",
      "free": true,
      "price": 0,
      "previousPrice": 88,
      "type": "2串1",
      "matchNum": 2,
      "matchZh": "英格兰 vs 加纳",
      "home": "England",
      "away": "Ghana",
      "matchTime": "06/24",
      "matchInfoId": 5403441,
      "expert": {
        "name": "许炜廷",
        "avatar": "https://relottery.ws.126.net/user/snapshot/20220301/XpsUE0z.jpg",
        "slogan": "足球分析师",
        "desc": "曾任职数据公司区域负责人，有一定的圈中人脉。",
        "hitRate": 0.5,
        "recent": "近8场中4场",
        "follower": 1283,
        "planCount": 41,
        "maxWin": 11
      },
      "link": "https://hongcai.163.com/thread.html?threadId=3502444",
      "unlocked": false,
      "content": "",
      "recommends": [],
      "recentForm": [],
      "jcNum": "",
      "homeIcon": "",
      "awayIcon": ""
    },
    {
      "threadId": 3502820,
      "title": "【世界杯】粮食不收年年种，不出大冷天天等。",
      "publishTime": "12小时前发布",
      "free": true,
      "price": 0,
      "previousPrice": 88,
      "type": "单场",
      "matchNum": 1,
      "matchZh": "巴拿马 vs 克罗地亚",
      "home": "Panama",
      "away": "Croatia",
      "matchTime": "06/24",
      "matchInfoId": 5403442,
      "expert": {
        "name": "匣内金刀",
        "avatar": "https://relottery.ws.126.net/user/20170220/LzUlrN.jpg",
        "slogan": "足球分析师",
        "desc": "热衷法系足球分析，常研究法甲、法乙和各项法国杯赛。",
        "hitRate": 0.42,
        "recent": "近12场中5场",
        "follower": 15493,
        "planCount": 42,
        "maxWin": 8
      },
      "link": "https://hongcai.163.com/thread.html?threadId=3502820",
      "unlocked": true,
      "content": "<p>巴拿马VS克罗地亚</p><p>本届世界杯还没开始，就有很多人说今年扩军了会有很多冷门。结果打到现在，104场比赛都打完44场了，还没有出现过3挡以上直接跪的大冷，此前我出击了2次都扛着卷刃刀回来。今天我决定第3次出手，希望这把能摸住大奶。</p><p>巴拿马世界排名第34位，总身价却只有3500万欧，典型的有实力没名气，具备了爆冷的基本要素。</p><p>随着阵容老化，克罗地亚以往每逢大赛最擅长的迷魂大法玩不起来了。巅峰时期的克罗地亚最厉害的就是控场能力，即使对手是巴西和西班牙这种技术好的球队，克罗地亚也能把节奏牢牢的掌握在自己手中。</p><p>没了控场能力导致球队防守直线下滑，而进攻便秘又是多年的老寒腿。现在这支克罗地亚已经是大不如前，整体实力衰退严重。</p><p>而克罗地亚的世界排名只比巴拿马高了23位，实力差距没有名气上那么大。那这场就有了抓大奶的机会了，还是前两天我说的那句话，宁可抓错也不能放过。</p><p>果菜推荐：巴拿马 胜</p><p>赛果预计：巴拿马2-1 3-1</p>",
      "recommends": [
        {
          "play": "让球",
          "code": "HDA",
          "items": [
            {
              "name": "主胜",
              "odds": 6.9,
              "rec": true
            },
            {
              "name": "平",
              "odds": 4.3,
              "rec": false
            },
            {
              "name": "客胜",
              "odds": 1.33,
              "rec": false
            }
          ]
        },
        {
          "play": "比分",
          "code": "FBF",
          "items": [
            {
              "name": "3:1",
              "odds": 70,
              "rec": true
            },
            {
              "name": "2:1",
              "odds": 18,
              "rec": true
            }
          ]
        }
      ],
      "recentForm": [
        {
          "date": "26-06-18",
          "home": "加纳",
          "hs": 1,
          "as": 0,
          "away": "巴拿马",
          "half": "0-0",
          "handicap": -0.5,
          "ou": 2.5
        },
        {
          "date": "26-06-07",
          "home": "巴拿马",
          "hs": 1,
          "as": 1,
          "away": "波黑",
          "half": "1-1",
          "handicap": 0.25,
          "ou": 2.25
        },
        {
          "date": "26-06-04",
          "home": "巴拿马",
          "hs": 4,
          "as": 2,
          "away": "多米尼加",
          "half": "2-0",
          "handicap": -1.75,
          "ou": 3.25
        },
        {
          "date": "26-06-01",
          "home": "巴西",
          "hs": 6,
          "as": 2,
          "away": "巴拿马",
          "half": "2-1",
          "handicap": -2.25,
          "ou": 3.25
        }
      ],
      "jcNum": "周二047",
      "homeIcon": "https://relottery.ws.126.net/thread/snapshot/20260402/DxCQYGI.png",
      "awayIcon": "https://relottery.ws.126.net/thread/snapshot/20260402/rgofn0z.png"
    }
  ]
}